README.rst
setup.py
pyfolder/__init__.py
pyfolder.egg-info/PKG-INFO
pyfolder.egg-info/SOURCES.txt
pyfolder.egg-info/dependency_links.txt
pyfolder.egg-info/not-zip-safe
pyfolder.egg-info/top_level.txt
pyfolder/interpreters/__init__.py
pyfolder/tests/__init__.py
pyfolder/tests/test_interpreters.py
pyfolder/tests/test_pyfolder.py