Metadata-Version: 1.1
Name: pyfolder
Version: 0.0.1
Summary: PyFolder is a package for managing filesystem folders as a dictionary.
Home-page: http://github.com/ipazc/pyfolder
Author: Iván de Paz Centeno
Author-email: ipazc@unileon.es
License: MIT
Keywords: pyfolder dict folder file filesystem
Platform: UNKNOWN
Classifier: Environment :: Console
Classifier: Intended Audience :: Developers
Classifier: Intended Audience :: Education
Classifier: Intended Audience :: Science/Research
Classifier: Natural Language :: English
Classifier: Programming Language :: Python :: 3.4
Classifier: Programming Language :: Python :: 3.5
Classifier: Programming Language :: Python :: 3.6
Classifier: Programming Language :: Python :: 3.7
